icefile/__init__.py
icefile-1.1.0.dist-info/METADATA
icefile-1.1.0.dist-info/WHEEL
icefile-1.1.0.dist-info/top_level.txt
icefile-1.1.0.dist-info/RECORD
