Metadata-Version: 2.1
Name: icefile
Version: 1.1.0
Summary: This module can be more convenient to operate files
Author: ice
Author-email: bilibili_wulihb@outlook.com
Classifier: Programming Language :: Python :: 3
Classifier: License :: OSI Approved :: MIT License
Classifier: Operating System :: OS Independent
